setup.py
NBTParse.egg-info/PKG-INFO
NBTParse.egg-info/SOURCES.txt
NBTParse.egg-info/dependency_links.txt
NBTParse.egg-info/entry_points.txt
NBTParse.egg-info/not-zip-safe
NBTParse.egg-info/top_level.txt
nbtparse/__init__.py
nbtparse/__version__.txt
nbtparse/_utils.py
nbtparse/_utils.pyi
nbtparse/exceptions.py
nbtparse/minecraft/__init__.py
nbtparse/minecraft/entity.py
nbtparse/minecraft/entity_ids.py
nbtparse/minecraft/entityfactory.py
nbtparse/minecraft/ids.py
nbtparse/minecraft/item.py
nbtparse/minecraft/level.py
nbtparse/minecraft/mobs.py
nbtparse/minecraft/projectile.py
nbtparse/minecraft/standard.json
nbtparse/minecraft/terrain/__init__.py
nbtparse/minecraft/terrain/_cVoxel.c
nbtparse/minecraft/terrain/_voxel.py
nbtparse/minecraft/terrain/chunk.py
nbtparse/minecraft/terrain/chunk.pyi
nbtparse/minecraft/terrain/dimension.py
nbtparse/minecraft/terrain/dimension.pyi
nbtparse/minecraft/terrain/filters.py
nbtparse/minecraft/terrain/region.py
nbtparse/minecraft/terrain/region.pyi
nbtparse/minecraft/terrain/tile.py
nbtparse/minecraft/terrain/voxel.pyi
nbtparse/semantics/__init__.py
nbtparse/semantics/fields.py
nbtparse/semantics/filetype.py
nbtparse/semantics/nbtobject.py
nbtparse/syntax/__init__.py
nbtparse/syntax/tags.py