Metadata-Version: 1.1
Name: NBTParse
Version: 0.7.1
Summary: NBT swiss army knife
Home-page: https://nbtparse.org
Author: Kevin Norris
Author-email: nykevin.norris@gmail.com
License: BSD (3-clause)
Platform: UNKNOWN
Classifier: Development Status :: 2 - Pre-Alpha
Classifier: License :: OSI Approved :: BSD License
Classifier: Topic :: Games/Entertainment
Classifier: Topic :: Software Development :: Libraries
Classifier: Intended Audience :: Developers
Classifier: Operating System :: OS Independent
Classifier: Programming Language :: Python :: 3
